rightmove_floorscraper/__init__.py
rightmove_floorscraper-0.4.dist-info/DESCRIPTION.rst
rightmove_floorscraper-0.4.dist-info/METADATA
rightmove_floorscraper-0.4.dist-info/RECORD
rightmove_floorscraper-0.4.dist-info/WHEEL
rightmove_floorscraper-0.4.dist-info/metadata.json
rightmove_floorscraper-0.4.dist-info/top_level.txt
