Metadata-Version: 2.0
Name: rightmove-floorscraper
Version: 0.4
Summary: A class for scraping floorplan data from rightmove.co.uk
Home-page: https://github.com/HarvsG/rightmove_webscraper.py
Author: CodingDoctor
Author-email: rightmovescraper@codingdoctor.co.uk
License: MIT
Keywords: webscraping,rightmove,data
Platform: UNKNOWN
Classifier: Development Status :: 4 - Beta
Classifier: Intended Audience :: End Users/Desktop
Classifier: License :: OSI Approved :: MIT License
Classifier: Programming Language :: Python :: 3.6
Requires-Dist: pandas
Requires-Dist: requests
Requires-Dist: lxml
